{
    "swagger": "2.0",
    "info": {
        "contact": {},
        "license": {}
    },
    "paths": {
        "/sessions": {
            "get": {
                "description": "get sessions",
                "consumes": [
                    "application/json"
                ],
                "produces": [
                    "application/json"
                ],
                "tags": [
                    "sessions"
                ],
                "summary": "List sessions",
                "parameters": [
                    {
                        "type": "string",
                        "format": "email",
                        "description": "name search by q",
                        "name": "q",
                        "in": "query"
                    }
                ]
            }
        }
    }
}